{
    "api": {
        "results": 1,
        "fixtures": [
            {
                "fixture_id": 284,
                "league_id": 2,
                "league": {
                    "name": "Premier League",
                    "country": "England",
                    "logo": "https:\/\/media.api-sports.io\/football\/leagues\/39.png",
                    "flag": "https:\/\/media.api-sports.io\/flags\/gb.svg"
                },
                "event_date": "2019-01-12T12:30:00+00:00",
                "event_timestamp": 1547296200,
                "firstHalfStart": 1547296200,
                "secondHalfStart": 1547299800,
                "round": "Regular Season - 22",
                "status": "Match Finished",
                "statusShort": "FT",
                "elapsed": 90,
                "venue": "London Stadium",
                "referee": "Jonathan Moss, England",
                "homeTeam": {
                    "team_id": 48,
                    "team_name": "West Ham",
                    "logo": "https:\/\/media.api-sports.io\/football\/teams\/48.png"
                },
                "awayTeam": {
                    "team_id": 42,
                    "team_name": "Arsenal",
                    "logo": "https:\/\/media.api-sports.io\/football\/teams\/42.png"
                },
                "goalsHomeTeam": 1,
                "goalsAwayTeam": 0,
                "score": {
                    "halftime": "0-0",
                    "fulltime": "1-0",
                    "extratime": null,
                    "penalty": null
                },
                "events": [
                    {
                        "elapsed": 46,
                        "elapsed_plus": null,
                        "team_id": 42,
                        "teamName": "Arsenal",
                        "player_id": 1448,
                        "player": "Shkodran Mustafi",
                        "assist_id": null,
                        "assist": null,
                        "type": "Card",
                        "detail": "Yellow Card",
                        "comments": null
                    },
                    {
                        "elapsed": 48,
                        "elapsed_plus": null,
                        "team_id": 48,
                        "teamName": "West Ham",
                        "player_id": 2937,
                        "player": "D. Rice",
                        "assist_id": 18825,
                        "assist": "S. Nasri",
                        "type": "Goal",
                        "detail": "Normal Goal",
                        "comments": null
                    },
                    {
                        "elapsed": 59,
                        "elapsed_plus": null,
                        "team_id": 42,
                        "teamName": "Arsenal",
                        "player_id": 1448,
                        "player": "S. Mustafi",
                        "assist_id": 1459,
                        "assist": "A. Ramsey",
                        "type": "subst",
                        "detail": "A. Ramsey",
                        "comments": null
                    },
                    {
                        "elapsed": 59,
                        "elapsed_plus": null,
                        "team_id": 42,
                        "teamName": "Arsenal",
                        "player_id": 1464,
                        "player": "G. Xhaka",
                        "assist_id": 1462,
                        "assist": "L. Torreira",
                        "type": "subst",
                        "detail": "L. Torreira",
                        "comments": null
                    },
                    {
                        "elapsed": 60,
                        "elapsed_plus": null,
                        "team_id": 42,
                        "teamName": "Arsenal",
                        "player_id": 1442,
                        "player": "Sead Kola\u0161inac",
                        "assist_id": null,
                        "assist": null,
                        "type": "Card",
                        "detail": "Yellow Card",
                        "comments": null
                    },
                    {
                        "elapsed": 69,
                        "elapsed_plus": null,
                        "team_id": 42,
                        "teamName": "Arsenal",
                        "player_id": 1456,
                        "player": "A. Maitland-Niles",
                        "assist_id": 1439,
                        "assist": "Beller\u00edn",
                        "type": "subst",
                        "detail": "Beller\u00edn",
                        "comments": null
                    },
                    {
                        "elapsed": 71,
                        "elapsed_plus": null,
                        "team_id": 48,
                        "teamName": "West Ham",
                        "player_id": 18830,
                        "player": "M. Arnautovi\u0107",
                        "assist_id": 18831,
                        "assist": "A. Carroll",
                        "type": "subst",
                        "detail": "A. Carroll",
                        "comments": null
                    },
                    {
                        "elapsed": 71,
                        "elapsed_plus": null,
                        "team_id": 48,
                        "teamName": "West Ham",
                        "player_id": 18825,
                        "player": "S. Nasri",
                        "assist_id": 18828,
                        "assist": "R. Snodgrass",
                        "type": "subst",
                        "detail": "R. Snodgrass",
                        "comments": null
                    },
                    {
                        "elapsed": 82,
                        "elapsed_plus": null,
                        "team_id": 48,
                        "teamName": "West Ham",
                        "player_id": 18819,
                        "player": "M. Antonio",
                        "assist_id": 18824,
                        "assist": "Pedro Obiang",
                        "type": "subst",
                        "detail": "Pedro Obiang",
                        "comments": null
                    }
                ],
                "lineups": {
                    "West Ham": {
                        "coach": "M. Pellegrini",
                        "coach_id": 3,
                        "formation": "4-2-3-1",
                        "startXI": [
                            {
                                "team_id": 48,
                                "player_id": 2997,
                                "player": "\u0141. Fabia\u0144ski",
                                "number": 1,
                                "pos": "G"
                            },
                            {
                                "team_id": 48,
                                "player_id": 18818,
                                "player": "P. Zabaleta",
                                "number": 5,
                                "pos": "D"
                            },
                            {
                                "team_id": 48,
                                "player_id": 18817,
                                "player": "A. Ogbonna",
                                "number": 21,
                                "pos": "D"
                            },
                            {
                                "team_id": 48,
                                "player_id": 18813,
                                "player": "A. Cresswell",
                                "number": 3,
                                "pos": "D"
                            },
                            {
                                "team_id": 48,
                                "player_id": 18814,
                                "player": "I. Diop",
                                "number": 23,
                                "pos": "D"
                            },
                            {
                                "team_id": 48,
                                "player_id": 18825,
                                "player": "S. Nasri",
                                "number": 18,
                                "pos": "M"
                            },
                            {
                                "team_id": 48,
                                "player_id": 18826,
                                "player": "M. Noble",
                                "number": 16,
                                "pos": "M"
                            },
                            {
                                "team_id": 48,
                                "player_id": 18819,
                                "player": "M. Antonio",
                                "number": 30,
                                "pos": "M"
                            },
                            {
                                "team_id": 48,
                                "player_id": 2412,
                                "player": "Felipe Anderson",
                                "number": 8,
                                "pos": "M"
                            },
                            {
                                "team_id": 48,
                                "player_id": 2937,
                                "player": "D. Rice",
                                "number": 41,
                                "pos": "M"
                            },
                            {
                                "team_id": 48,
                                "player_id": 18830,
                                "player": "M. Arnautovi\u0107",
                                "number": 7,
                                "pos": "F"
                            }
                        ],
                        "substitutes": [
                            {
                                "team_id": 48,
                                "player_id": 18831,
                                "player": "A. Carroll",
                                "number": 9,
                                "pos": "F"
                            },
                            {
                                "team_id": 48,
                                "player_id": 18828,
                                "player": "R. Snodgrass",
                                "number": 11,
                                "pos": "M"
                            },
                            {
                                "team_id": 48,
                                "player_id": 18824,
                                "player": "Pedro Obiang",
                                "number": 14,
                                "pos": "M"
                            },
                            {
                                "team_id": 48,
                                "player_id": 18812,
                                "player": "Adri\u00e1n",
                                "number": 13,
                                "pos": "G"
                            },
                            {
                                "team_id": 48,
                                "player_id": 18816,
                                "player": "A. Masuaku",
                                "number": 26,
                                "pos": "D"
                            },
                            {
                                "team_id": 48,
                                "player_id": 18833,
                                "player": "Lucas P\u00e9rez",
                                "number": 27,
                                "pos": "F"
                            },
                            {
                                "team_id": 48,
                                "player_id": 18821,
                                "player": "G. Diangana",
                                "number": 45,
                                "pos": "M"
                            }
                        ]
                    },
                    "Arsenal": {
                        "coach": "Unai Emery",
                        "coach_id": 18,
                        "formation": "3-4-2-1",
                        "startXI": [
                            {
                                "team_id": 42,
                                "player_id": 1438,
                                "player": "B. Leno",
                                "number": 19,
                                "pos": "G"
                            },
                            {
                                "team_id": 42,
                                "player_id": 1450,
                                "player": "S. Papastathopoulos",
                                "number": 5,
                                "pos": "D"
                            },
                            {
                                "team_id": 42,
                                "player_id": 1443,
                                "player": "L. Koscielny",
                                "number": 6,
                                "pos": "D"
                            },
                            {
                                "team_id": 42,
                                "player_id": 1448,
                                "player": "S. Mustafi",
                                "number": 20,
                                "pos": "D"
                            },
                            {
                                "team_id": 42,
                                "player_id": 1442,
                                "player": "S. Kola\u0161inac",
                                "number": 31,
                                "pos": "M"
                            },
                            {
                                "team_id": 42,
                                "player_id": 1464,
                                "player": "G. Xhaka",
                                "number": 34,
                                "pos": "M"
                            },
                            {
                                "team_id": 42,
                                "player_id": 1455,
                                "player": "A. Iwobi",
                                "number": 17,
                                "pos": "F"
                            },
                            {
                                "team_id": 42,
                                "player_id": 1456,
                                "player": "A. Maitland-Niles",
                                "number": 15,
                                "pos": "M"
                            },
                            {
                                "team_id": 42,
                                "player_id": 1454,
                                "player": "M. Guendouzi",
                                "number": 29,
                                "pos": "M"
                            },
                            {
                                "team_id": 42,
                                "player_id": 1465,
                                "player": "P. Aubameyang",
                                "number": 14,
                                "pos": "F"
                            },
                            {
                                "team_id": 42,
                                "player_id": 1467,
                                "player": "A. Lacazette",
                                "number": 9,
                                "pos": "F"
                            }
                        ],
                        "substitutes": [
                            {
                                "team_id": 42,
                                "player_id": 1459,
                                "player": "A. Ramsey",
                                "number": 8,
                                "pos": "M"
                            },
                            {
                                "team_id": 42,
                                "player_id": 1462,
                                "player": "L. Torreira",
                                "number": 11,
                                "pos": "M"
                            },
                            {
                                "team_id": 42,
                                "player_id": 1439,
                                "player": "Beller\u00edn",
                                "number": 2,
                                "pos": "D"
                            },
                            {
                                "team_id": 42,
                                "player_id": 1436,
                                "player": "P. \u010cech",
                                "number": 1,
                                "pos": "G"
                            },
                            {
                                "team_id": 42,
                                "player_id": 1444,
                                "player": "S. Lichtsteiner",
                                "number": 12,
                                "pos": "D"
                            },
                            {
                                "team_id": 42,
                                "player_id": 1447,
                                "player": "Nacho Monreal",
                                "number": 18,
                                "pos": "D"
                            },
                            {
                                "team_id": 42,
                                "player_id": 1468,
                                "player": "E. Nketiah",
                                "number": 49,
                                "pos": "F"
                            }
                        ]
                    }
                },
                "statistics": {
                    "Shots on Goal": {
                        "home": "3",
                        "away": "2"
                    },
                    "Shots off Goal": {
                        "home": "7",
                        "away": "8"
                    },
                    "Total Shots": {
                        "home": "11",
                        "away": "11"
                    },
                    "Blocked Shots": {
                        "home": "1",
                        "away": "1"
                    },
                    "Shots insidebox": {
                        "home": "7",
                        "away": "6"
                    },
                    "Shots outsidebox": {
                        "home": "4",
                        "away": "5"
                    },
                    "Fouls": {
                        "home": "7",
                        "away": "10"
                    },
                    "Corner Kicks": {
                        "home": "7",
                        "away": "3"
                    },
                    "Offsides": {
                        "home": "5",
                        "away": "3"
                    },
                    "Ball Possession": {
                        "home": "41%",
                        "away": "59%"
                    },
                    "Yellow Cards": {
                        "home": "0",
                        "away": "2"
                    },
                    "Red Cards": {
                        "home": null,
                        "away": null
                    },
                    "Goalkeeper Saves": {
                        "home": "3",
                        "away": "2"
                    },
                    "Total passes": {
                        "home": "380",
                        "away": "555"
                    },
                    "Passes accurate": {
                        "home": "307",
                        "away": "479"
                    },
                    "Passes %": {
                        "home": "81%",
                        "away": "86%"
                    }
                },
                "players": [
                    {
                        "event_id": 284,
                        "updateAt": 1589295706,
                        "player_id": 2997,
                        "player_name": "\u0141ukasz Fabia\u0144ski",
                        "team_id": 48,
                        "team_name": "West Ham",
                        "number": 1,
                        "position": "G",
                        "rating": "7.3",
                        "minutes_played": 90,
                        "captain": "False",
                        "substitute": "False",
                        "offsides": null,
                        "shots": {
                            "total": 0,
                            "on": 0
                        },
                        "goals": {
                            "total": 0,
                            "conceded": 0,
                            "assists": 0,
                            "saves": 3
                        },
                        "passes": {
                            "total": 19,
                            "key": 0,
                            "accuracy": 52
                        },
                        "tackles": {
                            "total": 0,
                            "blocks": 0,
                            "interceptions": 0
                        },
                        "duels": {
                            "total": 1,
                            "won": 1
                        },
                        "dribbles": {
                            "attempts": 0,
                            "success": 0,
                            "past": 0
                        },
                        "fouls": {
                            "drawn": 0,
                            "committed": 0
                        },
                        "cards": {
                            "yellow": 0,
                            "red": 0
                        },
                        "penalty": {
                            "won": 0,
                            "commited": 0,
                            "success": 0,
                            "missed": 0,
                            "saved": 0
                        }
                    },
                    {
                        "event_id": 284,
                        "updateAt": 1589295706,
                        "player_id": 18818,
                        "player_name": "Pablo Zabaleta",
                        "team_id": 48,
                        "team_name": "West Ham",
                        "number": 5,
                        "position": "D",
                        "rating": "7.0",
                        "minutes_played": 90,
                        "captain": "False",
                        "substitute": "False",
                        "offsides": null,
                        "shots": {
                            "total": 0,
                            "on": 0
                        },
                        "goals": {
                            "total": 0,
                            "conceded": 0,
                            "assists": 0,
                            "saves": 0
                        },
                        "passes": {
                            "total": 23,
                            "key": 1,
                            "accuracy": 85
                        },
                        "tackles": {
                            "total": 0,
                            "blocks": 0,
                            "interceptions": 3
                        },
                        "duels": {
                            "total": 5,
                            "won": 2
                        },
                        "dribbles": {
                            "attempts": 1,
                            "success": 1,
                            "past": 2
                        },
                        "fouls": {
                            "drawn": 1,
                            "committed": 0
                        },
                        "cards": {
                            "yellow": 0,
                            "red": 0
                        },
                        "penalty": {
                            "won": 0,
                            "commited": 0,
                            "success": 0,
                            "missed": 0,
                            "saved": 0
                        }
                    },
                    {
                        "event_id": 284,
                        "updateAt": 1589295706,
                        "player_id": 18814,
                        "player_name": "Issa Diop",
                        "team_id": 48,
                        "team_name": "West Ham",
                        "number": 23,
                        "position": "D",
                        "rating": "7.2",
                        "minutes_played": 90,
                        "captain": "False",
                        "substitute": "False",
                        "offsides": null,
                        "shots": {
                            "total": 0,
                            "on": 0
                        },
                        "goals": {
                            "total": 0,
                            "conceded": 0,
                            "assists": 0,
                            "saves": 0
                        },
                        "passes": {
                            "total": 32,
                            "key": 0,
                            "accuracy": 88
                        },
                        "tackles": {
                            "total": 2,
                            "blocks": 0,
                            "interceptions": 2
                        },
                        "duels": {
                            "total": 5,
                            "won": 4
                        },
                        "dribbles": {
                            "attempts": 0,
                            "success": 0,
                            "past": 0
                        },
                        "fouls": {
                            "drawn": 1,
                            "committed": 0
                        },
                        "cards": {
                            "yellow": 0,
                            "red": 0
                        },
                        "penalty": {
                            "won": 0,
                            "commited": 0,
                            "success": 0,
                            "missed": 0,
                            "saved": 0
                        }
                    },
                    {
                        "event_id": 284,
                        "updateAt": 1589295706,
                        "player_id": 18817,
                        "player_name": "Angelo Ogbonna",
                        "team_id": 48,
                        "team_name": "West Ham",
                        "number": 21,
                        "position": "D",
                        "rating": "7.2",
                        "minutes_played": 90,
                        "captain": "False",
                        "substitute": "False",
                        "offsides": null,
                        "shots": {
                            "total": 1,
                            "on": 0
                        },
                        "goals": {
                            "total": 0,
                            "conceded": 0,
                            "assists": 0,
                            "saves": 0
                        },
                        "passes": {
                            "total": 24,
                            "key": 0,
                            "accuracy": 88
                        },
                        "tackles": {
                            "total": 1,
                            "blocks": 0,
                            "interceptions": 3
                        },
                        "duels": {
                            "total": 3,
                            "won": 3
                        },
                        "dribbles": {
                            "attempts": 0,
                            "success": 0,
                            "past": 0
                        },
                        "fouls": {
                            "drawn": 1,
                            "committed": 0
                        },
                        "cards": {
                            "yellow": 0,
                            "red": 0
                        },
                        "penalty": {
                            "won": 0,
                            "commited": 0,
                            "success": 0,
                            "missed": 0,
                            "saved": 0
                        }
                    },
                    {
                        "event_id": 284,
                        "updateAt": 1589295706,
                        "player_id": 18813,
                        "player_name": "Aaron Cresswell",
                        "team_id": 48,
                        "team_name": "West Ham",
                        "number": 3,
                        "position": "D",
                        "rating": "7.3",
                        "minutes_played": 90,
                        "captain": "False",
                        "substitute": "False",
                        "offsides": null,
                        "shots": {
                            "total": 1,
                            "on": 0
                        },
                        "goals": {
                            "total": 0,
                            "conceded": 0,
                            "assists": 0,
                            "saves": 0
                        },
                        "passes": {
                            "total": 22,
                            "key": 1,
                            "accuracy": 78
                        },
                        "tackles": {
                            "total": 2,
                            "blocks": 0,
                            "interceptions": 3
                        },
                        "duels": {
                            "total": 7,
                            "won": 5
                        },
                        "dribbles": {
                            "attempts": 1,
                            "success": 1,
                            "past": 1
                        },
                        "fouls": {
                            "drawn": 0,
                            "committed": 0
                        },
                        "cards": {
                            "yellow": 0,
                            "red": 0
                        },
                        "penalty": {
                            "won": 0,
                            "commited": 0,
                            "success": 0,
                            "missed": 0,
                            "saved": 0
                        }
                    },
                    {
                        "event_id": 284,
                        "updateAt": 1589295706,
                        "player_id": 18826,
                        "player_name": "Mark Noble",
                        "team_id": 48,
                        "team_name": "West Ham",
                        "number": 16,
                        "position": "M",
                        "rating": "6.7",
                        "minutes_played": 90,
                        "captain": "True",
                        "substitute": "False",
                        "offsides": null,
                        "shots": {
                            "total": 1,
                            "on": 1
                        },
                        "goals": {
                            "total": 0,
                            "conceded": 0,
                            "assists": 0,
                            "saves": 0
                        },
                        "passes": {
                            "total": 41,
                            "key": 0,
                            "accuracy": 87
                        },
                        "tackles": {
                            "total": 0,
                            "blocks": 0,
                            "interceptions": 1
                        },
                        "duels": {
                            "total": 8,
                            "won": 1
                        },
                        "dribbles": {
                            "attempts": 0,
                            "success": 0,
                            "past": 3
                        },
                        "fouls": {
                            "drawn": 1,
                            "committed": 2
                        },
                        "cards": {
                            "yellow": 0,
                            "red": 0
                        },
                        "penalty": {
                            "won": 0,
                            "commited": 0,
                            "success": 0,
                            "missed": 0,
                            "saved": 0
                        }
                    },
                    {
                        "event_id": 284,
                        "updateAt": 1589295706,
                        "player_id": 2937,
                        "player_name": "Declan Rice",
                        "team_id": 48,
                        "team_name": "West Ham",
                        "number": 41,
                        "position": "M",
                        "rating": "7.8",
                        "minutes_played": 90,
                        "captain": "False",
                        "substitute": "False",
                        "offsides": null,
                        "shots": {
                            "total": 2,
                            "on": 1
                        },
                        "goals": {
                            "total": 1,
                            "conceded": 0,
                            "assists": 0,
                            "saves": 0
                        },
                        "passes": {
                            "total": 36,
                            "key": 0,
                            "accuracy": 85
                        },
                        "tackles": {
                            "total": 2,
                            "blocks": 1,
                            "interceptions": 3
                        },
                        "duels": {
                            "total": 8,
                            "won": 6
                        },
                        "dribbles": {
                            "attempts": 1,
                            "success": 1,
                            "past": 1
                        },
                        "fouls": {
                            "drawn": 1,
                            "committed": 0
                        },
                        "cards": {
                            "yellow": 0,
                            "red": 0
                        },
                        "penalty": {
                            "won": 0,
                            "commited": 0,
                            "success": 0,
                            "missed": 0,
                            "saved": 0
                        }
                    },
                    {
                        "event_id": 284,
                        "updateAt": 1589295706,
                        "player_id": 18819,
                        "player_name": "Michail Antonio",
                        "team_id": 48,
                        "team_name": "West Ham",
                        "number": 30,
                        "position": "M",
                        "rating": "6.5",
                        "minutes_played": 82,
                        "captain": "False",
                        "substitute": "False",
                        "offsides": 1,
                        "shots": {
                            "total": 2,
                            "on": 1
                        },
                        "goals": {
                            "total": 0,
                            "conceded": 0,
                            "assists": 0,
                            "saves": 0
                        },
                        "passes": {
                            "total": 19,
                            "key": 0,
                            "accuracy": 79
                        },
                        "tackles": {
                            "total": 0,
                            "blocks": 0,
                            "interceptions": 1
                        },
                        "duels": {
                            "total": 13,
                            "won": 5
                        },
                        "dribbles": {
                            "attempts": 6,
                            "success": 2,
                            "past": 0
                        },
                        "fouls": {
                            "drawn": 2,
                            "committed": 0
                        },
                        "cards": {
                            "yellow": 0,
                            "red": 0
                        },
                        "penalty": {
                            "won": 0,
                            "commited": 0,
                            "success": 0,
                            "missed": 0,
                            "saved": 0
                        }
                    },
                    {
                        "event_id": 284,
                        "updateAt": 1589295706,
                        "player_id": 18825,
                        "player_name": "Samir Nasri",
                        "team_id": 48,
                        "team_name": "West Ham",
                        "number": 18,
                        "position": "M",
                        "rating": "7.0",
                        "minutes_played": 71,
                        "captain": "False",
                        "substitute": "False",
                        "offsides": 2,
                        "shots": {
                            "total": 1,
                            "on": 0
                        },
                        "goals": {
                            "total": 0,
                            "conceded": 0,
                            "assists": 1,
                            "saves": 0
                        },
                        "passes": {
                            "total": 27,
                            "key": 3,
                            "accuracy": 84
                        },
                        "tackles": {
                            "total": 0,
                            "blocks": 0,
                            "interceptions": 0
                        },
                        "duels": {
                            "total": 4,
                            "won": 1
                        },
                        "dribbles": {
                            "attempts": 2,
                            "success": 1,
                            "past": 0
                        },
                        "fouls": {
                            "drawn": 0,
                            "committed": 2
                        },
                        "cards": {
                            "yellow": 0,
                            "red": 0
                        },
                        "penalty": {
                            "won": 0,
                            "commited": 0,
                            "success": 0,
                            "missed": 0,
                            "saved": 0
                        }
                    },
                    {
                        "event_id": 284,
                        "updateAt": 1589295706,
                        "player_id": 2412,
                        "player_name": "Felipe Anderson",
                        "team_id": 48,
                        "team_name": "West Ham",
                        "number": 8,
                        "position": "M",
                        "rating": "7.7",
                        "minutes_played": 90,
                        "captain": "False",
                        "substitute": "False",
                        "offsides": null,
                        "shots": {
                            "total": 2,
                            "on": 0
                        },
                        "goals": {
                            "total": 0,
                            "conceded": 0,
                            "assists": 0,
                            "saves": 0
                        },
                        "passes": {
                            "total": 30,
                            "key": 4,
                            "accuracy": 78
                        },
                        "tackles": {
                            "total": 3,
                            "blocks": 0,
                            "interceptions": 1
                        },
                        "duels": {
                            "total": 18,
                            "won": 9
                        },
                        "dribbles": {
                            "attempts": 7,
                            "success": 5,
                            "past": 3
                        },
                        "fouls": {
                            "drawn": 1,
                            "committed": 1
                        },
                        "cards": {
                            "yellow": 0,
                            "red": 0
                        },
                        "penalty": {
                            "won": 0,
                            "commited": 0,
                            "success": 0,
                            "missed": 0,
                            "saved": 0
                        }
                    },
                    {
                        "event_id": 284,
                        "updateAt": 1589295706,
                        "player_id": 18830,
                        "player_name": "Marko Arnautovi\u0107",
                        "team_id": 48,
                        "team_name": "West Ham",
                        "number": 7,
                        "position": "F",
                        "rating": "6.6",
                        "minutes_played": 71,
                        "captain": "False",
                        "substitute": "False",
                        "offsides": 1,
                        "shots": {
                            "total": 1,
                            "on": 0
                        },
                        "goals": {
                            "total": 0,
                            "conceded": 0,
                            "assists": 0,
                            "saves": 0
                        },
                        "passes": {
                            "total": 16,
                            "key": 1,
                            "accuracy": 80
                        },
                        "tackles": {
                            "total": 0,
                            "blocks": 0,
                            "interceptions": 0
                        },
                        "duels": {
                            "total": 3,
                            "won": 0
                        },
                        "dribbles": {
                            "attempts": 0,
                            "success": 0,
                            "past": 1
                        },
                        "fouls": {
                            "drawn": 0,
                            "committed": 1
                        },
                        "cards": {
                            "yellow": 0,
                            "red": 0
                        },
                        "penalty": {
                            "won": 0,
                            "commited": 0,
                            "success": 0,
                            "missed": 0,
                            "saved": 0
                        }
                    },
                    {
                        "event_id": 284,
                        "updateAt": 1589295706,
                        "player_id": 18828,
                        "player_name": "Robert Snodgrass",
                        "team_id": 48,
                        "team_name": "West Ham",
                        "number": 11,
                        "position": "M",
                        "rating": "6.2",
                        "minutes_played": 19,
                        "captain": "False",
                        "substitute": "True",
                        "offsides": null,
                        "shots": {
                            "total": 0,
                            "on": 0
                        },
                        "goals": {
                            "total": 0,
                            "conceded": 0,
                            "assists": 0,
                            "saves": 0
                        },
                        "passes": {
                            "total": 4,
                            "key": 0,
                            "accuracy": 66
                        },
                        "tackles": {
                            "total": 0,
                            "blocks": 0,
                            "interceptions": 0
                        },
                        "duels": {
                            "total": 2,
                            "won": 0
                        },
                        "dribbles": {
                            "attempts": 0,
                            "success": 0,
                            "past": 2
                        },
                        "fouls": {
                            "drawn": 0,
                            "committed": 0
                        },
                        "cards": {
                            "yellow": 0,
                            "red": 0
                        },
                        "penalty": {
                            "won": 0,
                            "commited": 0,
                            "success": 0,
                            "missed": 0,
                            "saved": 0
                        }
                    },
                    {
                        "event_id": 284,
                        "updateAt": 1589295706,
                        "player_id": 18824,
                        "player_name": "Pedro Obiang",
                        "team_id": 48,
                        "team_name": "West Ham",
                        "number": 14,
                        "position": "M",
                        "rating": "6.8",
                        "minutes_played": 8,
                        "captain": "False",
                        "substitute": "True",
                        "offsides": null,
                        "shots": {
                            "total": 0,
                            "on": 0
                        },
                        "goals": {
                            "total": 0,
                            "conceded": 0,
                            "assists": 0,
                            "saves": 0
                        },
                        "passes": {
                            "total": 6,
                            "key": 0,
                            "accuracy": 100
                        },
                        "tackles": {
                            "total": 1,
                            "blocks": 0,
                            "interceptions": 0
                        },
                        "duels": {
                            "total": 4,
                            "won": 3
                        },
                        "dribbles": {
                            "attempts": 1,
                            "success": 1,
                            "past": 0
                        },
                        "fouls": {
                            "drawn": 1,
                            "committed": 0
                        },
                        "cards": {
                            "yellow": 0,
                            "red": 0
                        },
                        "penalty": {
                            "won": 0,
                            "commited": 0,
                            "success": 0,
                            "missed": 0,
                            "saved": 0
                        }
                    },
                    {
                        "event_id": 284,
                        "updateAt": 1589295706,
                        "player_id": 18831,
                        "player_name": "Andy Carroll",
                        "team_id": 48,
                        "team_name": "West Ham",
                        "number": 9,
                        "position": "F",
                        "rating": "6.6",
                        "minutes_played": 19,
                        "captain": "False",
                        "substitute": "True",
                        "offsides": 1,
                        "shots": {
                            "total": 0,
                            "on": 0
                        },
                        "goals": {
                            "total": 0,
                            "conceded": 0,
                            "assists": 0,
                            "saves": 0
                        },
                        "passes": {
                            "total": 8,
                            "key": 0,
                            "accuracy": 72
                        },
                        "tackles": {
                            "total": 0,
                            "blocks": 0,
                            "interceptions": 0
                        },
                        "duels": {
                            "total": 8,
                            "won": 5
                        },
                        "dribbles": {
                            "attempts": 1,
                            "success": 0,
                            "past": 1
                        },
                        "fouls": {
                            "drawn": 1,
                            "committed": 1
                        },
                        "cards": {
                            "yellow": 0,
                            "red": 0
                        },
                        "penalty": {
                            "won": 0,
                            "commited": 0,
                            "success": 0,
                            "missed": 0,
                            "saved": 0
                        }
                    },
                    {
                        "event_id": 284,
                        "updateAt": 1589295706,
                        "player_id": 1438,
                        "player_name": "Bernd Leno",
                        "team_id": 42,
                        "team_name": "Arsenal",
                        "number": 19,
                        "position": "G",
                        "rating": "6.6",
                        "minutes_played": 90,
                        "captain": "False",
                        "substitute": "False",
                        "offsides": null,
                        "shots": {
                            "total": 0,
                            "on": 0
                        },
                        "goals": {
                            "total": 0,
                            "conceded": 1,
                            "assists": 0,
                            "saves": 2
                        },
                        "passes": {
                            "total": 26,
                            "key": 0,
                            "accuracy": 78
                        },
                        "tackles": {
                            "total": 0,
                            "blocks": 0,
                            "interceptions": 0
                        },
                        "duels": {
                            "total": 0,
                            "won": 0
                        },
                        "dribbles": {
                            "attempts": 0,
                            "success": 0,
                            "past": 0
                        },
                        "fouls": {
                            "drawn": 0,
                            "committed": 0
                        },
                        "cards": {
                            "yellow": 0,
                            "red": 0
                        },
                        "penalty": {
                            "won": 0,
                            "commited": 0,
                            "success": 0,
                            "missed": 0,
                            "saved": 0
                        }
                    },
                    {
                        "event_id": 284,
                        "updateAt": 1589295706,
                        "player_id": 1448,
                        "player_name": "Shkodran Mustafi",
                        "team_id": 42,
                        "team_name": "Arsenal",
                        "number": 20,
                        "position": "D",
                        "rating": "6.7",
                        "minutes_played": 59,
                        "captain": "False",
                        "substitute": "False",
                        "offsides": null,
                        "shots": {
                            "total": 0,
                            "on": 0
                        },
                        "goals": {
                            "total": 0,
                            "conceded": 0,
                            "assists": 0,
                            "saves": 0
                        },
                        "passes": {
                            "total": 34,
                            "key": 0,
                            "accuracy": 89
                        },
                        "tackles": {
                            "total": 2,
                            "blocks": 0,
                            "interceptions": 1
                        },
                        "duels": {
                            "total": 6,
                            "won": 4
                        },
                        "dribbles": {
                            "attempts": 1,
                            "success": 1,
                            "past": 0
                        },
                        "fouls": {
                            "drawn": 0,
                            "committed": 1
                        },
                        "cards": {
                            "yellow": 1,
                            "red": 0
                        },
                        "penalty": {
                            "won": 0,
                            "commited": 0,
                            "success": 0,
                            "missed": 0,
                            "saved": 0
                        }
                    },
                    {
                        "event_id": 284,
                        "updateAt": 1589295706,
                        "player_id": 1450,
                        "player_name": "Sokratis",
                        "team_id": 42,
                        "team_name": "Arsenal",
                        "number": 5,
                        "position": "D",
                        "rating": "7.0",
                        "minutes_played": 90,
                        "captain": "False",
                        "substitute": "False",
                        "offsides": null,
                        "shots": {
                            "total": 0,
                            "on": 0
                        },
                        "goals": {
                            "total": 0,
                            "conceded": 0,
                            "assists": 0,
                            "saves": 0
                        },
                        "passes": {
                            "total": 65,
                            "key": 0,
                            "accuracy": 97
                        },
                        "tackles": {
                            "total": 3,
                            "blocks": 1,
                            "interceptions": 1
                        },
                        "duels": {
                            "total": 7,
                            "won": 4
                        },
                        "dribbles": {
                            "attempts": 1,
                            "success": 1,
                            "past": 0
                        },
                        "fouls": {
                            "drawn": 0,
                            "committed": 1
                        },
                        "cards": {
                            "yellow": 0,
                            "red": 0
                        },
                        "penalty": {
                            "won": 0,
                            "commited": 0,
                            "success": 0,
                            "missed": 0,
                            "saved": 0
                        }
                    },
                    {
                        "event_id": 284,
                        "updateAt": 1589295706,
                        "player_id": 1443,
                        "player_name": "Laurent Koscielny",
                        "team_id": 42,
                        "team_name": "Arsenal",
                        "number": 6,
                        "position": "D",
                        "rating": "6.8",
                        "minutes_played": 90,
                        "captain": "True",
                        "substitute": "False",
                        "offsides": null,
                        "shots": {
                            "total": 0,
                            "on": 0
                        },
                        "goals": {
                            "total": 0,
                            "conceded": 0,
                            "assists": 0,
                            "saves": 0
                        },
                        "passes": {
                            "total": 88,
                            "key": 0,
                            "accuracy": 97
                        },
                        "tackles": {
                            "total": 2,
                            "blocks": 0,
                            "interceptions": 0
                        },
                        "duels": {
                            "total": 7,
                            "won": 4
                        },
                        "dribbles": {
                            "attempts": 0,
                            "success": 0,
                            "past": 2
                        },
                        "fouls": {
                            "drawn": 1,
                            "committed": 0
                        },
                        "cards": {
                            "yellow": 0,
                            "red": 0
                        },
                        "penalty": {
                            "won": 0,
                            "commited": 0,
                            "success": 0,
                            "missed": 0,
                            "saved": 0
                        }
                    },
                    {
                        "event_id": 284,
                        "updateAt": 1589295706,
                        "player_id": 1456,
                        "player_name": "Ainsley Maitland-Niles",
                        "team_id": 42,
                        "team_name": "Arsenal",
                        "number": 15,
                        "position": "M",
                        "rating": "6.6",
                        "minutes_played": 69,
                        "captain": "False",
                        "substitute": "False",
                        "offsides": null,
                        "shots": {
                            "total": 0,
                            "on": 0
                        },
                        "goals": {
                            "total": 0,
                            "conceded": 0,
                            "assists": 0,
                            "saves": 0
                        },
                        "passes": {
                            "total": 13,
                            "key": 0,
                            "accuracy": 65
                        },
                        "tackles": {
                            "total": 1,
                            "blocks": 0,
                            "interceptions": 3
                        },
                        "duels": {
                            "total": 7,
                            "won": 3
                        },
                        "dribbles": {
                            "attempts": 3,
                            "success": 2,
                            "past": 1
                        },
                        "fouls": {
                            "drawn": 0,
                            "committed": 0
                        },
                        "cards": {
                            "yellow": 0,
                            "red": 0
                        },
                        "penalty": {
                            "won": 0,
                            "commited": 0,
                            "success": 0,
                            "missed": 0,
                            "saved": 0
                        }
                    },
                    {
                        "event_id": 284,
                        "updateAt": 1589295706,
                        "player_id": 1454,
                        "player_name": "Matt\u00e9o Guendouzi",
                        "team_id": 42,
                        "team_name": "Arsenal",
                        "number": 29,
                        "position": "M",
                        "rating": "7.1",
                        "minutes_played": 90,
                        "captain": "False",
                        "substitute": "False",
                        "offsides": null,
                        "shots": {
                            "total": 3,
                            "on": 1
                        },
                        "goals": {
                            "total": 0,
                            "conceded": 0,
                            "assists": 0,
                            "saves": 0
                        },
                        "passes": {
                            "total": 57,
                            "key": 0,
                            "accuracy": 90
                        },
                        "tackles": {
                            "total": 0,
                            "blocks": 0,
                            "interceptions": 1
                        },
                        "duels": {
                            "total": 7,
                            "won": 4
                        },
                        "dribbles": {
                            "attempts": 2,
                            "success": 1,
                            "past": 2
                        },
                        "fouls": {
                            "drawn": 3,
                            "committed": 0
                        },
                        "cards": {
                            "yellow": 0,
                            "red": 0
                        },
                        "penalty": {
                            "won": 0,
                            "commited": 0,
                            "success": 0,
                            "missed": 0,
                            "saved": 0
                        }
                    },
                    {
                        "event_id": 284,
                        "updateAt": 1589295706,
                        "player_id": 1464,
                        "player_name": "Granit Xhaka",
                        "team_id": 42,
                        "team_name": "Arsenal",
                        "number": 34,
                        "position": "M",
                        "rating": "5.9",
                        "minutes_played": 59,
                        "captain": "False",
                        "substitute": "False",
                        "offsides": null,
                        "shots": {
                            "total": 0,
                            "on": 0
                        },
                        "goals": {
                            "total": 0,
                            "conceded": 0,
                            "assists": 0,
                            "saves": 0
                        },
                        "passes": {
                            "total": 34,
                            "key": 1,
                            "accuracy": 85
                        },
                        "tackles": {
                            "total": 1,
                            "blocks": 0,
                            "interceptions": 1
                        },
                        "duels": {
                            "total": 5,
                            "won": 3
                        },
                        "dribbles": {
                            "attempts": 1,
                            "success": 1,
                            "past": 2
                        },
                        "fouls": {
                            "drawn": 0,
                            "committed": 0
                        },
                        "cards": {
                            "yellow": 0,
                            "red": 0
                        },
                        "penalty": {
                            "won": 0,
                            "commited": 0,
                            "success": 0,
                            "missed": 0,
                            "saved": 0
                        }
                    },
                    {
                        "event_id": 284,
                        "updateAt": 1589295706,
                        "player_id": 1442,
                        "player_name": "Sead Kola\u0161inac",
                        "team_id": 42,
                        "team_name": "Arsenal",
                        "number": 31,
                        "position": "M",
                        "rating": "6.9",
                        "minutes_played": 90,
                        "captain": "False",
                        "substitute": "False",
                        "offsides": 2,
                        "shots": {
                            "total": 0,
                            "on": 0
                        },
                        "goals": {
                            "total": 0,
                            "conceded": 0,
                            "assists": 0,
                            "saves": 0
                        },
                        "passes": {
                            "total": 34,
                            "key": 1,
                            "accuracy": 82
                        },
                        "tackles": {
                            "total": 2,
                            "blocks": 0,
                            "interceptions": 1
                        },
                        "duels": {
                            "total": 4,
                            "won": 2
                        },
                        "dribbles": {
                            "attempts": 0,
                            "success": 0,
                            "past": 0
                        },
                        "fouls": {
                            "drawn": 0,
                            "committed": 2
                        },
                        "cards": {
                            "yellow": 1,
                            "red": 0
                        },
                        "penalty": {
                            "won": 0,
                            "commited": 0,
                            "success": 0,
                            "missed": 0,
                            "saved": 0
                        }
                    },
                    {
                        "event_id": 284,
                        "updateAt": 1589295706,
                        "player_id": 1465,
                        "player_name": "Pierre-Emerick Aubameyang",
                        "team_id": 42,
                        "team_name": "Arsenal",
                        "number": 14,
                        "position": "F",
                        "rating": "6.5",
                        "minutes_played": 90,
                        "captain": "False",
                        "substitute": "False",
                        "offsides": null,
                        "shots": {
                            "total": 3,
                            "on": 0
                        },
                        "goals": {
                            "total": 0,
                            "conceded": 0,
                            "assists": 0,
                            "saves": 0
                        },
                        "passes": {
                            "total": 12,
                            "key": 1,
                            "accuracy": 70
                        },
                        "tackles": {
                            "total": 0,
                            "blocks": 0,
                            "interceptions": 1
                        },
                        "duels": {
                            "total": 7,
                            "won": 1
                        },
                        "dribbles": {
                            "attempts": 1,
                            "success": 0,
                            "past": 2
                        },
                        "fouls": {
                            "drawn": 0,
                            "committed": 2
                        },
                        "cards": {
                            "yellow": 0,
                            "red": 0
                        },
                        "penalty": {
                            "won": 0,
                            "commited": 0,
                            "success": 0,
                            "missed": 0,
                            "saved": 0
                        }
                    },
                    {
                        "event_id": 284,
                        "updateAt": 1589295706,
                        "player_id": 1455,
                        "player_name": "Alex Iwobi",
                        "team_id": 42,
                        "team_name": "Arsenal",
                        "number": 17,
                        "position": "F",
                        "rating": "7.4",
                        "minutes_played": 90,
                        "captain": "False",
                        "substitute": "False",
                        "offsides": null,
                        "shots": {
                            "total": 1,
                            "on": 0
                        },
                        "goals": {
                            "total": 0,
                            "conceded": 0,
                            "assists": 0,
                            "saves": 0
                        },
                        "passes": {
                            "total": 33,
                            "key": 2,
                            "accuracy": 78
                        },
                        "tackles": {
                            "total": 1,
                            "blocks": 0,
                            "interceptions": 1
                        },
                        "duels": {
                            "total": 11,
                            "won": 7
                        },
                        "dribbles": {
                            "attempts": 7,
                            "success": 6,
                            "past": 0
                        },
                        "fouls": {
                            "drawn": 0,
                            "committed": 0
                        },
                        "cards": {
                            "yellow": 0,
                            "red": 0
                        },
                        "penalty": {
                            "won": 0,
                            "commited": 0,
                            "success": 0,
                            "missed": 0,
                            "saved": 0
                        }
                    },
                    {
                        "event_id": 284,
                        "updateAt": 1589295706,
                        "player_id": 1467,
                        "player_name": "Alexandre Lacazette",
                        "team_id": 42,
                        "team_name": "Arsenal",
                        "number": 9,
                        "position": "F",
                        "rating": "7.0",
                        "minutes_played": 90,
                        "captain": "False",
                        "substitute": "False",
                        "offsides": 1,
                        "shots": {
                            "total": 4,
                            "on": 1
                        },
                        "goals": {
                            "total": 0,
                            "conceded": 0,
                            "assists": 0,
                            "saves": 0
                        },
                        "passes": {
                            "total": 22,
                            "key": 0,
                            "accuracy": 73
                        },
                        "tackles": {
                            "total": 2,
                            "blocks": 0,
                            "interceptions": 0
                        },
                        "duels": {
                            "total": 18,
                            "won": 8
                        },
                        "dribbles": {
                            "attempts": 2,
                            "success": 2,
                            "past": 2
                        },
                        "fouls": {
                            "drawn": 1,
                            "committed": 4
                        },
                        "cards": {
                            "yellow": 0,
                            "red": 0
                        },
                        "penalty": {
                            "won": 0,
                            "commited": 0,
                            "success": 0,
                            "missed": 0,
                            "saved": 0
                        }
                    },
                    {
                        "event_id": 284,
                        "updateAt": 1589295706,
                        "player_id": 1439,
                        "player_name": "H\u00e9ctor Beller\u00edn",
                        "team_id": 42,
                        "team_name": "Arsenal",
                        "number": 2,
                        "position": "D",
                        "rating": "6.6",
                        "minutes_played": 21,
                        "captain": "False",
                        "substitute": "False",
                        "offsides": null,
                        "shots": {
                            "total": 0,
                            "on": 0
                        },
                        "goals": {
                            "total": 0,
                            "conceded": 0,
                            "assists": 0,
                            "saves": 0
                        },
                        "passes": {
                            "total": 10,
                            "key": 0,
                            "accuracy": 76
                        },
                        "tackles": {
                            "total": 0,
                            "blocks": 0,
                            "interceptions": 1
                        },
                        "duels": {
                            "total": 2,
                            "won": 1
                        },
                        "dribbles": {
                            "attempts": 0,
                            "success": 0,
                            "past": 0
                        },
                        "fouls": {
                            "drawn": 1,
                            "committed": 0
                        },
                        "cards": {
                            "yellow": 0,
                            "red": 0
                        },
                        "penalty": {
                            "won": 0,
                            "commited": 0,
                            "success": 0,
                            "missed": 0,
                            "saved": 0
                        }
                    },
                    {
                        "event_id": 284,
                        "updateAt": 1589295706,
                        "player_id": 1462,
                        "player_name": "Lucas Torreira",
                        "team_id": 42,
                        "team_name": "Arsenal",
                        "number": 11,
                        "position": "M",
                        "rating": "6.6",
                        "minutes_played": 31,
                        "captain": "False",
                        "substitute": "False",
                        "offsides": null,
                        "shots": {
                            "total": 0,
                            "on": 0
                        },
                        "goals": {
                            "total": 0,
                            "conceded": 0,
                            "assists": 0,
                            "saves": 0
                        },
                        "passes": {
                            "total": 26,
                            "key": 0,
                            "accuracy": 89
                        },
                        "tackles": {
                            "total": 1,
                            "blocks": 0,
                            "interceptions": 0
                        },
                        "duels": {
                            "total": 4,
                            "won": 2
                        },
                        "dribbles": {
                            "attempts": 0,
                            "success": 0,
                            "past": 1
                        },
                        "fouls": {
                            "drawn": 1,
                            "committed": 0
                        },
                        "cards": {
                            "yellow": 0,
                            "red": 0
                        },
                        "penalty": {
                            "won": 0,
                            "commited": 0,
                            "success": 0,
                            "missed": 0,
                            "saved": 0
                        }
                    },
                    {
                        "event_id": 284,
                        "updateAt": 1589295706,
                        "player_id": 1459,
                        "player_name": "Aaron Ramsey",
                        "team_id": 42,
                        "team_name": "Arsenal",
                        "number": 8,
                        "position": "M",
                        "rating": "6.6",
                        "minutes_played": 31,
                        "captain": "False",
                        "substitute": "False",
                        "offsides": null,
                        "shots": {
                            "total": 0,
                            "on": 0
                        },
                        "goals": {
                            "total": 0,
                            "conceded": 0,
                            "assists": 0,
                            "saves": 0
                        },
                        "passes": {
                            "total": 25,
                            "key": 2,
                            "accuracy": 78
                        },
                        "tackles": {
                            "total": 1,
                            "blocks": 0,
                            "interceptions": 0
                        },
                        "duels": {
                            "total": 4,
                            "won": 1
                        },
                        "dribbles": {
                            "attempts": 1,
                            "success": 0,
                            "past": 0
                        },
                        "fouls": {
                            "drawn": 0,
                            "committed": 0
                        },
                        "cards": {
                            "yellow": 0,
                            "red": 0
                        },
                        "penalty": {
                            "won": 0,
                            "commited": 0,
                            "success": 0,
                            "missed": 0,
                            "saved": 0
                        }
                    }
                ]
            }
        ]
    }
}